weaviate/__init__.py
weaviate/auth.py
weaviate/client.py
weaviate/embedded.py
weaviate/error_msgs.py
weaviate/exceptions.py
weaviate/types.py
weaviate/util.py
weaviate/version.py
weaviate/warnings.py
weaviate/backup/__init__.py
weaviate/backup/backup.py
weaviate/batch/__init__.py
weaviate/batch/crud_batch.py
weaviate/batch/requests.py
weaviate/classification/__init__.py
weaviate/classification/classification.py
weaviate/classification/config_builder.py
weaviate/cluster/__init__.py
weaviate/cluster/cluster.py
weaviate/connect/__init__.py
weaviate/connect/authentication.py
weaviate/connect/connection.py
weaviate/contextionary/__init__.py
weaviate/contextionary/crud_contextionary.py
weaviate/data/__init__.py
weaviate/data/crud_data.py
weaviate/data/references/__init__.py
weaviate/data/references/crud_references.py
weaviate/data/replication/__init__.py
weaviate/data/replication/replication.py
weaviate/gql/__init__.py
weaviate/gql/aggregate.py
weaviate/gql/filter.py
weaviate/gql/get.py
weaviate/gql/multi_get.py
weaviate/gql/query.py
weaviate/schema/__init__.py
weaviate/schema/crud_schema.py
weaviate/schema/validate_schema.py
weaviate/schema/properties/__init__.py
weaviate/schema/properties/crud_properties.py
weaviate/wcs/__init__.py
weaviate/wcs/crud_wcs.py
weaviate_client_samos123-3.26.0.dist-info/LICENSE.md
weaviate_client_samos123-3.26.0.dist-info/METADATA
weaviate_client_samos123-3.26.0.dist-info/WHEEL
weaviate_client_samos123-3.26.0.dist-info/top_level.txt
weaviate_client_samos123-3.26.0.dist-info/RECORD
