Metadata-Version: 2.1
Name: weaviate-client-samos123
Version: 3.26.0
Summary: A python native weaviate client
Home-page: https://github.com/weaviate/weaviate-python-client
Author: SeMI Technologies
Author-email: hello@weaviate.io,
Project-URL: Documentation, https://weaviate-python-client.readthedocs.io
Project-URL: Source, https://github.com/weaviate/weaviate-python-client
Project-URL: Tracker, https://github.com/weaviate/weaviate-python-client/issues
Requires-Python: >=3.7
License-File: LICENSE.md
Requires-Dist: requests (<2.29.0,>=2.28.0)
Requires-Dist: validators (<0.20.0,>=0.18.2)
Requires-Dist: tqdm (<5.0.0,>=4.59.0)
Requires-Dist: authlib (>=1.1.0)
